midnight/__init__.py
midnight/__main__.py
midnight/midnight.py
midnight_engine-0.1.1.dist-info/LICENSE
midnight_engine-0.1.1.dist-info/METADATA
midnight_engine-0.1.1.dist-info/WHEEL
midnight_engine-0.1.1.dist-info/top_level.txt
midnight_engine-0.1.1.dist-info/RECORD
