Metadata-Version: 2.1
Name: midnight-engine
Version: 0.1.1
Summary: python terminal game engine with a simple yet powerful 🚀 codebase
Author: TVRework
License: MIT
Platform: unix
Platform: linux
Platform: osx
Platform: cygwin
Platform: win32
Classifier: Programming Language :: Python :: 3
Classifier: Programming Language :: Python :: 3 :: Only
Classifier: Programming Language :: Python :: 3.7
Classifier: Programming Language :: Python :: 3.8
Classifier: Programming Language :: Python :: 3.9
Requires-Python: >=3.7
License-File: LICENSE
Requires-Dist: pyfiglet (>=0.8)
